escolors/__init__.py
escolors/estypes.py
escolors/termcolor.py
escolors-0.0.4.dist-info/METADATA
escolors-0.0.4.dist-info/WHEEL
escolors-0.0.4.dist-info/top_level.txt
escolors-0.0.4.dist-info/RECORD
